{
  "indexes": [
    {
      "collectionGroup": "notes",
      "queryScope": "COLLECTION",
      "fields": [
        { "fieldPath": "pinned", "order": "DESCENDING" },
        { "fieldPath": "createdAt", "order": "DESCENDING" }
      ]
    },
    {
      "collectionGroup": "album_items",
      "queryScope": "COLLECTION",
      "fields": [
        { "fieldPath": "albumId", "order": "ASCENDING" },
        { "fieldPath": "createdAt", "order": "DESCENDING" }
      ]
    },
    {
      "collectionGroup": "page_files",
      "queryScope": "COLLECTION",
      "fields": [
        { "fieldPath": "pageId", "order": "ASCENDING" },
        { "fieldPath": "createdAt", "order": "DESCENDING" }
      ]
    }
  ],
  "fieldOverrides": []
}
